{
 "intents": [
  {
   "item": [
    {
     "tag": "question_37_Answer",
     "patterns": [
      "Center (0, -4) r = 7",
      "(0, -4) 7"
     ],
     "responses": [
      "correct"
     ]
    },
    {
     "tag": "question_20_Answer",
     "patterns": [
      "center(3,0) radius=4",
      "center(3,0) r=4"
     ],
     "responses": [
      "correct"
     ]
    }
   ]
  },
  {
   "item": [
    {
     "tag": "question_37_Solution",
     "patterns": [
      "x^2 + y^2 +8y = 33 x^2 + y^2 + 8y + 16 = 33 + 16 x^2 + (y+4)^2 = 49",
      "x^2 + y^2 + 8y = 33 (4)^2 = 16 x^2 + y^2 + 8y + 16 = 33 + 16 x^2 + (y + 4)^2 = 49"
     ],
     "responses": [
      "correct"
     ]
    },
    {
     "tag": "question_20_Solution",
     "patterns": [
      "x^2+y^2-6x=7 x^2-6x+9+y^2=7+9 (x-3)^2+y^2=16",
      "x^2 + y^2 - 6x = 7 (-3)^2 = 9 x^2 - 6x + 9 + y^2 = 7 + 9 (x - 3)^2 + y^2 = 16"
     ],
     "responses": [
      "correct"
     ]
    }
   ]
  },
  {
   "item": [
    {
     "tag": "question_40_Answer",
     "patterns": [
      "(x - 7)^2 = 12(y - 6)",
      "(x - 7)^2 = 12(y - 6)"
     ],
     "responses": [
      "correct"
     ]
    },
    {
     "tag": "question_41_Answer",
     "patterns": [
      "(5, 0) x = -5",
      "(5, 0) x = -5"
     ],
     "responses": [
      "correct"
     ]
    }
   ]
  },
  {
   "item": [
    {
     "tag": "question_40_Solution",
     "patterns": [
      "2c = 9 - 3 = 6, c = 3. (7, 6)",
      "k = (9 + 3) / 2 = 6 p = (9 - 6) / 2 = 1.5 (x - 7)^2 = 4(1.5)(y - 6) (x - 7)^2 = 6(y - 6) (x - 7)^2 = 6y - 36 (x - 7)^2 = 12(y - 6)"
     ],
     "responses": [
      "correct"
     ]
    },
    {
     "tag": "question_41_Solution",
     "patterns": [
      "(0, 0) 4c = 20 c = 5",
      "(x - h)^2 = 4p(y - k) (0, 0) 4p = 20 p = 5 (5, 0) x = -5"
     ],
     "responses": [
      "correct"
     ]
    }
   ]
  },
  {
   "item": [
    {
     "tag": "question_21_Answer",
     "patterns": [
      "center(0,0)",
      "0,0"
     ],
     "responses": [
      "correct"
     ]
    },
    {
     "tag": "question_45_Answer",
     "patterns": [
      "Center: (0, 6)",
      "(0, 6)"
     ],
     "responses": [
      "correct"
     ]
    }
   ]
  },
  {
   "item": [
    {
     "tag": "question_21_Solution",
     "patterns": [
      "h=0 k=0",
      "(x - h)^2/a^2 + (y - k)^2/b^2 = 1 x^2/49 + y^2/169 = 1 (h, k) = (0, 0)"
     ],
     "responses": [
      "correct"
     ]
    },
    {
     "tag": "question_45_Solution",
     "patterns": [
      "(x-h)^2 /a^2+(y-k)^2/b^2=1 h=0 k=6",
      "(x - h)^2 / a^2 + (y - k)^2 / b^2 = 1 x^2 / 64 + (y - 6)^2 / 121 = 1 (h, k) = (0, 6)"
     ],
     "responses": [
      "correct"
     ]
    }
   ]
  },
  {
   "item": [
    {
     "tag": "question_49_Answer",
     "patterns": [
      "(-3,0) (3,0)",
      "-3,0 3,0"
     ],
     "responses": [
      "correct"
     ]
    },
    {
     "tag": "question_23_Answer",
     "patterns": [
      "(0, 5.83), (0, -5.83)",
      "(0, 5.83) (0, -5.83)"
     ],
     "responses": [
      "correct"
     ]
    }
   ]
  },
  {
   "item": [
    {
     "tag": "question_49_Solution",
     "patterns": [
      "x^2/a^2-y^2/b^2=1  (-a, 0) (a,0) a^2 = 9 a = V9 = 3",
      "x^2/9 - y^2/16 = 1 (x - h)^2/a^2 - (y - k)^2/b^2 = 1 (h, k) = (0, 0) a^2 = 9 a = 3 b^2 = 16 b = 4 (3, 0) (-3, 0)"
     ],
     "responses": [
      "correct"
     ]
    },
    {
     "tag": "question_23_Solution",
     "patterns": [
      "y^2/a^2 \u2013 x^2/b^2 = 1 a^2 = 25, b^2 = 9 a = 5, b = 3 c = V(a2 + b2) = V(52 + 32) =V34 = 5.83",
      "c = V(a^2 + b^2) c = V(25 + 9) V(34)  (0, V34) (0, -V34)"
     ],
     "responses": [
      "correct"
     ]
    }
   ]
  },
  {
   "item": [
    {
     "tag": "question_32_Answer",
     "patterns": [
      "(1,2) (0,1)",
      "(1,2) (0,1)"
     ],
     "responses": [
      "correct"
     ]
    },
    {
     "tag": "question_24_Answer",
     "patterns": [
      "(5,2)",
      "5,2"
     ],
     "responses": [
      "correct"
     ]
    }
   ]
  },
  {
   "item": [
    {
     "tag": "question_32_Solution",
     "patterns": [
      "-x - y = -1 + y = x^2 + 1 x - y + y = -1 + (x^2 + 1) x = 1, x = 0 x - y = -1 y=2 y=1",
      "x - (x^2 + 1) = -1 x - x^2 - 1 = -1 -x^2 + x - 1 = -1 -x^2 + x = 0  x(-x + 1) = 0 x = 0 -x + 1 = 0 -x = 1 x = 0 0 - y = -1 y = 1 x = 1 1 - y = -1 -y = -2 y = 2 (0, 1) (1, 2)"
     ],
     "responses": [
      "correct"
     ]
    },
    {
     "tag": "question_24_Solution",
     "patterns": [
      "x^2-(7-x)^2=21 14x-70=0 x=5",
      "x = 7 - y (7 - y)^2 - y^2 = 21 49 - 14y + y^2 - y^2 = 21 -14y = 21 - 49 -14y = -28 y = 2 x + 2 = 7  x = 7 - 2  x = 5"
     ],
     "responses": [
      "correct"
     ]
    }
   ]
  },
  {
   "item": [
    {
     "tag": "question_35_Answer",
     "patterns": [
      "x= -1/2 y=2",
      "x= -1/2 y=2"
     ],
     "responses": [
      "correct"
     ]
    },
    {
     "tag": "question_25_Answer",
     "patterns": [
      "y=2 x=-1/2",
      "y=2 x=-1/2"
     ],
     "responses": [
      "correct"
     ]
    }
   ]
  },
  {
   "item": [
    {
     "tag": "question_35_Solution",
     "patterns": [
      "2(x^2-y)=2(3) 2x^2-2y=6 2x^2\u22122y=6 -2x^2+6y=14 2y=-2 y=1 x^2-y=3 x^2-(1)=3 x^2=4 x=+/-2",
      "2(x^2 - y) = 2(3) 2x^2 - 2y = 6 2x^2 - 2y = 6 2x^2 + 6y = 14 (2x^2 + 6y) - (2x^2 - 2y) = 14 - 6 8y = 8 y = 1 x^2 - 1 = 3 x^2 = 4 x = +/-2 "
     ],
     "responses": [
      "correct"
     ]
    },
    {
     "tag": "question_25_Solution",
     "patterns": [
      "2x-3=-7 (-2)(2x-3y)=(-2)(-7) -4x+6y=14 4x+7y=12 13y=26 y=2 x=-1/2",
      "4(2x + 7) = 4(3y) 2(4x + 7y) = 2(12) 8x + 28 = 12y 8x + 14y = 24 (8x + 28) - (8x + 14y) = 12y - 24 28 - 14y = 12y - 24 -14y - 12y = -24 - 28  -26y = -52 y = 2 2x + 7 = 3(2) 2x + 7 = 6  2x = 6 - 7  2x = -1 x = -1/2"
     ],
     "responses": [
      "correct"
     ]
    }
   ]
  },
  {
   "item": [
    {
     "tag": "question_27_Answer",
     "patterns": [
      "(x-3)^2+(y+4)^2=21",
      "-"
     ],
     "responses": [
      "correct"
     ]
    },
    {
     "tag": "question_38_Answer",
     "patterns": [
      "(x+4)^2+(y-2)^2=5^2",
      "(x+4)^2+(y-2)^2=5^2"
     ],
     "responses": [
      "correct"
     ]
    }
   ]
  },
  {
   "item": [
    {
     "tag": "question_27_Solution",
     "patterns": [
      "x^2-6x+y^2+8y=-4 x^2-6x+9+y^2+8y+16=-4+9+16 (x-3)^2+(y+4)^2=21",
      "x^2 - 6x (-3)^2 = 9 y^2 + 8y (4)^2 = 16 x^2 - 6x + 9 + y^2 + 8y + 16 = -4 + 9 + 16 (x - 3)^2 + (y + 4)^2 = 21"
     ],
     "responses": [
      "correct"
     ]
    },
    {
     "tag": "question_38_Solution",
     "patterns": [
      "(x^2+8x)+(y^2-4y)=5 (x^2+8x+(8/2)^2)+(y^2-4y+(-4/2)^2)=5 + (8/2)^2 + (-4/2)^2 (x^2+8x+16)+(y^2-4y+4)=5+16+4 (x+4)^2+(y-2)^2=5^2",
      "x^2 + 8x (4)^2 = 16 y^2 - 4y (-2)^2 = 4 x^2 + 8x + 16 + y^2 - 4y + 4 = 5 + 16 + 4 (x + 4)^2 + (y - 2)^2 = 25 (x + 4)^2 + (y - 2)^2 = 25"
     ],
     "responses": [
      "correct"
     ]
    }
   ]
  },
  {
   "item": [
    {
     "tag": "question_43_Answer",
     "patterns": [
      "f(x)=(x-12)^2+13",
      "(x-12)^2+13"
     ],
     "responses": [
      "correct"
     ]
    },
    {
     "tag": "question_42_Answer",
     "patterns": [
      "(-28,-4)",
      "(-28,-4)"
     ],
     "responses": [
      "correct"
     ]
    }
   ]
  },
  {
   "item": [
    {
     "tag": "question_43_Solution",
     "patterns": [
      "(-24/2)^2=(-12)^2=144 f(x)=x^2-24x+144-144+157",
      "x^2 - 24x + 157  x^2 - 24x + 157 + 144 - 144 (x^2 - 24x + 144) + 157 - 144 (x - 12)^2 + 13 a = 1 h = 12 k = 13 y = (x - 12)^2 + 13"
     ],
     "responses": [
      "correct"
     ]
    },
    {
     "tag": "question_42_Solution",
     "patterns": [
      "x=ay^2+by+c -(8/2(1))=-4 x=y^2+8y-12 x=(-4)^2+8(-4)-12=16+(-32)-12=-28",
      "x = y^2 + 8y - 12 y^2 + 8y = x + 12 y^2 + 8y + 4^2 = x + 12 + 4^2 (y + 4)^2 = x + 28  x = y^2 + 8y - 12 is (-28, -4)"
     ],
     "responses": [
      "correct"
     ]
    }
   ]
  },
  {
   "item": [
    {
     "tag": "question_46_Answer",
     "patterns": [
      "Center: (-1,5)",
      "(-1, 5)"
     ],
     "responses": [
      "correct"
     ]
    },
    {
     "tag": "question_47_Answer",
     "patterns": [
      "Center: (0, 3)",
      "(0, 3)"
     ],
     "responses": [
      "correct"
     ]
    }
   ]
  },
  {
   "item": [
    {
     "tag": "question_46_Solution",
     "patterns": [
      "(x-h)^2 /a^2+(y-k)^2/b^2=1 h=-1 k=5",
      "(x - 1)^2/9 + (y + 5)^2/4 = 1 (x - h)^2/a^2 + (y - k)^2/b^2 = 1 (h, k) = (1, -5) a^2 = 9 a = 3 b^2 = 4 b = 2 (1, -5)"
     ],
     "responses": [
      "correct"
     ]
    },
    {
     "tag": "question_47_Solution",
     "patterns": [
      "(x-h)^2 /a^2+(y-k)^2/b^2=1 h=0 k=3",
      "x^2/49 + (y - 3)^2/9 = 1 (x - h)^2/a^2 + (y - k)^2/b^2 = 1 (h, k) = (0, 3) a^2 = 49 a = 7 b^2 = 9 b = 3 (0, 3)"
     ],
     "responses": [
      "correct"
     ]
    }
   ]
  },
  {
   "item": [
    {
     "tag": "question_50_Answer",
     "patterns": [
      "(0, 5)(0, -5)",
      "0,5 0,-5"
     ],
     "responses": [
      "correct"
     ]
    },
    {
     "tag": "question_26_Answer",
     "patterns": [
      "(x+4)^2/5-(y-3)^2/4=1",
      "(x+4)^2/5-(y-3)^2/4=1"
     ],
     "responses": [
      "correct"
     ]
    }
   ]
  },
  {
   "item": [
    {
     "tag": "question_50_Solution",
     "patterns": [
      "(y^2/25)-(x^2/9) = 1 y^2/a^2 - x^2/b^2 = 1 a^2 = 25 b^2 = 9 a = 5 b = 3",
      "(y - k)^2 / a^2 - (x - h)^2 / b^2 = 1  (h, k) = (0, 0) a^2 = 25 b^2 = 9 (0, 5) (0, -5)"
     ],
     "responses": [
      "correct"
     ]
    },
    {
     "tag": "question_26_Solution",
     "patterns": [
      "4(x^2+8x)-5(y^2-6y)=1 4(x^2+8x+16)-5(y^2-6y+9)=1+4(16)-5(9) 4(x+4)^2-5(y-3)^2=20 (x+4)^2/5-(y-3)^2/4=1",
      "4x^2 - 5y^2 + 32x + 30y = 1 4(x^2 + 8x) - 5y^2 + 30y = 1 4(x^2 + 8x + 16) - 5y^2 + 30y = 1 + 4(16) 4(x + 4)^2 - 5y^2 + 30y = 1 + 64 4(x + 4)^2 - 5(y^2 - 6y) = 65 4(x + 4)^2 - 5(y^2 - 6y + 9) = 65 - 5(9) 4(x + 4)^2 - 5(y - 3)^2 = 20 4(x + 4)^2 / 20 - 5(y - 3)^2 / 20 = 1 (x + 4)^2 / 5 - (y - 3)^2 / 4 = 1 (x + 4)^2 / 5 - (y - 3)^2 / 4 = 1"
     ],
     "responses": [
      "correct"
     ]
    }
   ]
  },
  {
   "item": [
    {
     "tag": "question_33_Answer",
     "patterns": [
      "(6,9)(-6,-9)",
      "(6,9)(-6,-9)"
     ],
     "responses": [
      "correct"
     ]
    },
    {
     "tag": "question_30_Answer",
     "patterns": [
      "(4,-10),(-5,-19)",
      "(4,-10),(-5,-19)"
     ],
     "responses": [
      "correct"
     ]
    }
   ]
  },
  {
   "item": [
    {
     "tag": "question_33_Solution",
     "patterns": [
      "y=x+3 x^2+(x+3)^2 = 117 x^2+x^2+6x+9=117 2x^2+6x+9-117=0 2x^2+6x-108=0 2(x^2+3x-54)=0 2(x+9)(x-6)=0 x=6 x=-9 y=6+3=9 y=-9+3=-6",
      "y = x + 3 x^2 + (x + 3)^2 = 117 x^2 + (x^2 + 6x + 9) = 117 2x^2 + 6x + 9 = 117 2x^2 + 6x - 108 = 0 x^2 + 3x - 54 = 0 (x + 9)(x - 6) = 0 x = -9 x = 6 x = -9 y = -9 + 3 y = -6 x = 6 y = 6 + 3 y = 9 (-9, -6) (6, 9)"
     ],
     "responses": [
      "correct"
     ]
    },
    {
     "tag": "question_30_Solution",
     "patterns": [
      "x-y=14 y=x-14 x^2+y=6 x^2+(x-14)=6 x^2+x-14-6=0 x^2+x-20=0 (x+5)(x-4)=0 x=-5 x=4 x=-5 y=x-14=-19 x=4 y=x-14=-10",
      "x = y + 14 (y + 14)^2 + y = 6 y^2 + 28y + 196 + y = 6 y^2 + 29y + 196 = 6 y^2 + 29y + 190 = 0  y = (-b +/- V(b^2 - 4ac)) / (2a) y = (-29 +/- V(29^2 - 4(1)(190))) / (2(1)) y = (-29 +/- V(841 - 760)) / 2  y = (-29 +/- V81) / 2  y = (-29 +/- 9) / 2 y = -19 x = -19 + 14 = -5 y = -10 x = -10 + 14 = 4 (4, -10) (-5, -19)"
     ],
     "responses": [
      "correct"
     ]
    }
   ]
  },
  {
   "item": [
    {
     "tag": "question_28_Answer",
     "patterns": [
      "(-4,0),(4,0)",
      "(-4,0),(4,0)"
     ],
     "responses": [
      "correct"
     ]
    },
    {
     "tag": "question_29_Answer",
     "patterns": [
      "(-1,7),(-1,-1)",
      "(-1,7),(-1,-1)"
     ],
     "responses": [
      "correct"
     ]
    }
   ]
  },
  {
   "item": [
    {
     "tag": "question_28_Solution",
     "patterns": [
      "x^2+y^2=16 + x^2-y^2=16 x^2+y^2+(x^2-y^2)=16+16 2x^2=32 x=4 x=-4 y=0 y=0 (-4,0),(4,0)",
      "(x^2 + y^2) - (x^2 - y^2) = 16 - 16 2y^2 = 0 y^2 = 0  y = 0  x^2 + 0 = 16 x^2 = 16 x = +/-4"
     ],
     "responses": [
      "correct"
     ]
    },
    {
     "tag": "question_29_Solution",
     "patterns": [
      "4(3-x)=(y-3)^2 12-4x=y^2-6y+9 y^2+4x-6y=3 y^2-4x-6y=11 y^2-4x-6y=3 2y^2-12y=14 y^2-6y-7=0 (y-7)(y+1)=0 y=7 y=-1 x=3-((y-3)^2/4) y=7 x=-1 y=-1 x=-1",
      "4(3 - x) = (y - 3)^2 12 - 4x = y^2 - 6y + 9 y^2 + 4x - 6y = 3 y^2 - 4x - 6y = 11 y^2 + 4x - 6y = 3 2y^2 - 12y = 14 y^2 - 6y = 7 y^2 - 6y - 7 = 0 (y - 7)(y + 1) = 0 y = 7 y = -1 x = 3 - ((y - 3)^2 / 4) x = 3 - ((7 - 3)^2 / 4) y = 7 x = 3 - (16 / 4) x = 3 - 4 x = -1 y = -1 x = 3 - ((-1 - 3)^2 / 4) x = 3 - (16 / 4) x = 3 - 4 x = -1 (-1, 7) (-1, -1)"
     ],
     "responses": [
      "correct"
     ]
    }
   ]
  },
  {
   "item": [
    {
     "tag": "question_1_Answer",
     "patterns": [
      "x^2+y^2=9",
      "x^2 + y^2 = 9"
     ],
     "responses": [
      "correct"
     ]
    },
    {
     "tag": "question_36_Answer",
     "patterns": [
      "Center (-3, 5/4 ) r = 5.5",
      "(-3, 5/4 ) 5.5"
     ],
     "responses": [
      "correct"
     ]
    },
    {
     "tag": "question_2_Answer",
     "patterns": [
      "center=(7,-1) radius=6",
      "c=(7,-1) r=6"
     ],
     "responses": [
      "correct"
     ]
    }
   ]
  },
  {
   "item": [
    {
     "tag": "question_1_Solution",
     "patterns": [
      "(x-h)^2+(y-k)^2=r^2 (x-0)^2+(y-0)^2=3^2 x^2+y^2=9",
      "(x - 0)^2 + (y - 0)^2 = 3^2 x^2 + y^2 = 9 (0, 0) 3"
     ],
     "responses": [
      "correct"
     ]
    },
    {
     "tag": "question_36_Solution",
     "patterns": [
      "16(x^2 + 6x) + 16(y^2 -(5/2)y)= 315 16(x^2 + 6x + 9) + 16 (y^2 -(5/2)y + 25/16)= 315 + 16(9) + 16(25/16) 16(x + 3)^2 + 16( y -(5/4))^2= 484 (x + 3)^2 +(y -(5/4))^2 = 484/16=121/4=(11/2)^2",
      "16x^2 + 96x + 16y^2 - 40y = 315 x^2 + 6x + y^2 - 2.5y = 19.69 (3)^2 = 9 (-1.25)^2 = 1.5625 x^2 + 6x + 9 + y^2 - 2.5y + 1.5625 = 19.69 + 9 + 1.5625 (x + 3)^2 + (y - 1.25)^2 = 30.2525 -3, 1.25, 5.5"
     ],
     "responses": [
      "correct"
     ]
    },
    {
     "tag": "question_2_Solution",
     "patterns": [
      "x^2-14x+y^2+2y=-14 x^2-14x+49+y^2+2y+1=-14+49+1 (x-7)^2+(y+1)^2=36",
      "(x - h)^2 + (y - k)^2 = r^2 x^2 + y^2 - 14x + 2y = -14 (-7)^2 = 49 (1)^2 = 1 x^2 - 14x + 49 + y^2 + 2y + 1 = -14 + 49 + 1 (x - 7)^2 + (y + 1)^2 = 36 (7, -1), 6"
     ],
     "responses": [
      "correct"
     ]
    }
   ]
  },
  {
   "item": [
    {
     "tag": "question_4_Answer",
     "patterns": [
      "vertex=(-3,4) focus=1.2",
      "(-3,4) 1.2"
     ],
     "responses": [
      "correct"
     ]
    },
    {
     "tag": "question_39_Answer",
     "patterns": [
      "Focus: (0, -1) Directrix: y = 1",
      "(0, -1) 1"
     ],
     "responses": [
      "correct"
     ]
    },
    {
     "tag": "question_3_Answer",
     "patterns": [
      "vertex=(-4,-6) focus=1.25",
      "(-4,-6) 1.25"
     ],
     "responses": [
      "correct"
     ]
    }
   ]
  },
  {
   "item": [
    {
     "tag": "question_4_Solution",
     "patterns": [
      "5x^2+30x=-24y+51 5(x^2+6x+9)=-24+51+5(9) 5(x+3)^2=-24y+96=-24(y-4) (x+3)^2=-(24/5)(y-4)",
      "5x^2 + 30x + 24y = 51 x = -30 / (2 * 5) = -30 / 10 = -3 5(-3)^2 + 30(-3) + 24y = 51 45 - 90 + 24y = 51 -45 + 24y = 51 24y = 51 + 45 24y = 96 y = 96 / 24 y = 4 5x^2 + 30x + 24y = 51 (-3, 4) 24y = -5x^2 - 30x + 51 y = (-5/24)x^2 - (5/4)x + (51/24) a = -5/24 p = 1 / (4a) p = 1 / (4 * (-5/24)) p = 6/5"
     ],
     "responses": [
      "correct"
     ]
    },
    {
     "tag": "question_39_Solution",
     "patterns": [
      "3x^2 = -12y x^2 = -4y 4c = 4 c = 1 ",
      " x^2 = -4y c = 1 (0, -1) y = 1"
     ],
     "responses": [
      "correct"
     ]
    },
    {
     "tag": "question_3_Solution",
     "patterns": [
      "y^2+12y=5x-16 y^2+12y+36=5x-16+36 y^2+12y+36=5x-20 (y+6)^2=5(x+4)",
      "(y^2 + 12y) - 5x = -16 (y^2 + 12y + 36) - 5x = -16 + 36 (y + 6)^2 - 5x = 20 (y + 6)^2 = 5(x + 4) (y - k)^2 = 4a(x - h) y^2 - 5x + 12y = -16 y^2 + 12y - 5x = -16 (y^2 + 12y + 36) - 36 - 5x = -16 (y + 6)^2 - 36 - 5x = -16 (y + 6)^2 = 5x - 20 Focus = (0 + 5/4, -6) = (5/4, -6)"
     ],
     "responses": [
      "correct"
     ]
    }
   ]
  },
  {
   "item": [
    {
     "tag": "question_5_Answer",
     "patterns": [
      "(7,2)",
      "7,-2"
     ],
     "responses": [
      "correct"
     ]
    },
    {
     "tag": "question_44_Answer",
     "patterns": [
      "f1(-4, 0) f2(4, 0)",
      "(-4, 0) (4, 0)"
     ],
     "responses": [
      "correct"
     ]
    },
    {
     "tag": "question_6_Answer",
     "patterns": [
      "(-5.2,0) (5.2,0)",
      "-5.2,0 5.2,0"
     ],
     "responses": [
      "correct"
     ]
    }
   ]
  },
  {
   "item": [
    {
     "tag": "question_5_Solution",
     "patterns": [
      "9(x^2-14)+16y(y^2+4y)=71 9(x^2-14x+49)+16(y^2+4y+4)=71+9(49)+16(4) 9(x-7)^2+16(y+2)^2=576 ((x-7)^2/64)+((y+2)^2/35)=1",
      " 9x^2 - 126x + 16y^2 + 64y = 71 9(x^2 - 14x) + 16y^2 + 64y = 71 9(x^2 - 14x + 49) + 16y^2 + 64y = 71 + 9(49) 9(x - 7)^2 + 16y^2 + 64y = 512 9(x - 7)^2 + 16(y^2 + 4y) = 512 (4/2)^2 = 4 9(x - 7)^2 + 16(y^2 + 4y + 4) = 512 + 16(4) 9(x - 7)^2 + 16(y + 2)^2 = 576 [(x - 7)^2 / 64] + [(y + 2)^2 / 36] = 1 [(x - h)^2 / a^2] + [(y - k)^2 / b^2] = 1 (7, -2)"
     ],
     "responses": [
      "correct"
     ]
    },
    {
     "tag": "question_44_Solution",
     "patterns": [
      "a^2 = 25 b^2 = 9 a = 5 b = 3 c = Va^2 - b^2 = 4",
      "x^2/a^2) + (y^2/b^2) = 1 a^2 = 25 b^2 = 9 a = 5 b = 3 c = V(5^2 - 3^2) = V(25 - 9) = V(16) = 4 (4, 0) (-4, 0)"
     ],
     "responses": [
      "correct"
     ]
    },
    {
     "tag": "question_6_Solution",
     "patterns": [
      "c=va^2-b^2 c=v46-19 c=v27 c=5.2",
      "(x^2/a^2) + (y^2/b^2) = 1 a^2 = 46 b^2 = 19 c = V(46 - 19) = V27 = 5.196 (0 +/- 5.20, 0  (5.20, 0) and (-5.20, 0)"
     ],
     "responses": [
      "correct"
     ]
    }
   ]
  },
  {
   "item": [
    {
     "tag": "question_48_Answer",
     "patterns": [
      "y = -0.4x y = 0.4x",
      "y = -0.4x y = 0.4x"
     ],
     "responses": [
      "correct"
     ]
    },
    {
     "tag": "question_7_Answer",
     "patterns": [
      "(0,-5) (0,5)",
      "0,-5 0,5"
     ],
     "responses": [
      "correct"
     ]
    },
    {
     "tag": "question_8_Answer",
     "patterns": [
      "center = (7,-2)",
      "(7,-2)"
     ],
     "responses": [
      "correct"
     ]
    }
   ]
  },
  {
   "item": [
    {
     "tag": "question_48_Solution",
     "patterns": [
      "x^2/a^2-y^2/b^2=1 y = -(b/a)x y = (b/a)x a^2 = 25 a = V25 = 5 b^2 = 4 b = V4 = 2 b/a = 2/5 = 0.4",
      "x^2/25 - y^2/4 = 1 (x - h)^2/a^2 - (y - k)^2/b^2 = 1 (h, k) = (0, 0) a^2 = 25 a = 5 b^2 = 4 b = 2 y = 0 +/- (2/5)(x - 0) y = +/- (2/5)x  x^2/25 - y^2/4 = 1 y = (2/5)x y = -(2/5)x"
     ],
     "responses": [
      "correct"
     ]
    },
    {
     "tag": "question_7_Solution",
     "patterns": [
      "b^2=25 b=v25 b=5",
      "(y - h)^2/a^2 - (x - k)^2/b^2 = 1 a^2 = 25 b^2 = 64 a = 5 b = 8 y^2/25 - x^2/64 = 1 (0, 5) (0, -5)."
     ],
     "responses": [
      "correct"
     ]
    },
    {
     "tag": "question_8_Solution",
     "patterns": [
      "a^2=25 b^2=9 a=5 b=3 (y+2)^2/25-(x-7)^2/9=0 y+2=+/-(5/3)(x-7)",
      "(y + 2)^2/25 - (x - 7)^2/9 = 1 (7, -2)"
     ],
     "responses": [
      "correct"
     ]
    }
   ]
  },
  {
   "item": [
    {
     "tag": "question_13_Answer",
     "patterns": [
      "(-6,6),(4,6)",
      "-6,6 4,6"
     ],
     "responses": [
      "correct"
     ]
    },
    {
     "tag": "question_11_Answer",
     "patterns": [
      "x=2 y=-2",
      "x = 2 , y = -2"
     ],
     "responses": [
      "correct"
     ]
    },
    {
     "tag": "question_12_Answer",
     "patterns": [
      "(2,5),(3,7)",
      "2,5 3,7"
     ],
     "responses": [
      "correct"
     ]
    },
    {
     "tag": "question_14_Answer",
     "patterns": [
      "(2,V2),(2,-V2),(5,V23),(-5,-V23)",
      "2,V2,2,-V2,V23 -5,-V23"
     ],
     "responses": [
      "correct"
     ]
    },
    {
     "tag": "question_31_Answer",
     "patterns": [
      "(-2,5) (7,-22)",
      "(-2,5) (7,-22)"
     ],
     "responses": [
      "correct"
     ]
    },
    {
     "tag": "question_15_Answer",
     "patterns": [
      "x=2, y=0",
      "(2,0)"
     ],
     "responses": [
      "correct"
     ]
    }
   ]
  },
  {
   "item": [
    {
     "tag": "question_13_Solution",
     "patterns": [
      "4(6)=x^2+2x 0=x^2+2x=24 0=(x+6)(x-4) x=-6,4 4y=(-6)^2+2(-6) 4y=36-12 4y=24 y=6 4y=(4)^2+2(4) 4y=16+8 4y=24 y=6",
      "V(y^2) = V36 y = +/-6 4(6) = x^2 + 2x 24 = x^2 + 2x x^2 + 2x - 24 = 0 (x - 4)(x + 6) = 0 x = 4 x = -6 (4, 6) (-6, 6)"
     ],
     "responses": [
      "correct"
     ]
    },
    {
     "tag": "question_11_Solution",
     "patterns": [
      "4x+y=6 y=6-4x 5x+3y=4 5x+3(6-4x)=4 -7x+18=4 x=2 y=6-4(2) y=-2",
      "y = 6 - 4x 5x + 3(6 - 4x) = 4 5x + 18 - 12x = 4 -7x + 18 = 4 x = -14 / -7 x = 2 4(2) + y = 6 8 + y = 6 y = 6 - 8 y = -2  x = 2 y = -2"
     ],
     "responses": [
      "correct"
     ]
    },
    {
     "tag": "question_12_Solution",
     "patterns": [
      "-x^2+y+3x=7 y=x^2-3x+7 5=-y-x^2+7x y=x^2+7x-5 x^2-3x+7=-x^2+7x-5 2x^2-10x12=0 2(x^2-5x+6)=0 2(x-2)(x-3)=0 x=2,x=3 y=x^2-3x+7 y=(2)^2-3(2)+7=5 y=x^2-3x+7 y=(3)^2-3(3)+7=7",
      "-x^2 + y + 3x = 7 y = x^2 - 3x + 7 5 = -y -x^2 + 7x y = -x^2 + 7x - 5 x^2 - 3x + 7 = -x^2 + 7x - 5 2x^2 - 10x + 12 = 0 x^2 - 5x + 6 = 0  (x - 2)(x - 3) = 0 x = 2 x = 3 y = (2)^2 - 3(2) + 7 y = 4 - 6 + 7 y = 5 y = (3)^2 - 3(3) + 7 y = 9 - 9 + 7 y = 7"
     ],
     "responses": [
      "correct"
     ]
    },
    {
     "tag": "question_14_Solution",
     "patterns": [
      "(x^2-2)+x^2+6x=18 (x^2-2)+x^2+6x-18=0 2x^2+6x-20=0 2(x^2+3x-10)=0 2(x-2)(x+5)=0 x=2,-5 y^2=(2)^2-2 y^2=2 y=+/-V2 y^2=(-5)^2 -2 y^2=23 y=+/-V23",
      "y^2 = x^2 - 2 (x^2 - 2) + x^2 + 6x = 18 2x^2 + 6x - 20 = 0 x^2 + 3x - 10 = 0 x = 2 y^2 = 2^2 - 2 y^2 = 2 y = +/-V2 x = -5 y^2 = (-5)^2 - 2 y^2 = 23 y = +/-V23 (2, V2), (2, -V2), (-5, V23), (-5, -V23)"
     ],
     "responses": [
      "correct"
     ]
    },
    {
     "tag": "question_31_Solution",
     "patterns": [
      "-x^2+2x+13 y=x^2-8x-15 x^2-8x-15 2x^2-10x-28=0 2(x^2-5x-14)=0 2(x+2)(x-7)=0 x=-2,x=7 (-2)^2 - 8(-2)-15=5 (7)^2-8(7)-15=-2",
      "y = 13 - x^2 + 2x y = x^2 - 8x - 15 13 - x^2 + 2x = x^2 - 8x - 15 2x^2 - 10x + 28 = 0 x^2 - 5x + 14 = 0 x = (-(-5) +/- V((-5)^2 - 4(1)(14))) / (2(1)) x = (5 +/- V(25 + 56)) / 2 x = (5 +/- V81) / 2 x = (5 +/- 9) / 2 x1 = (5 + 9) / 2 = 7 x2 = (5 - 9) / 2 = -2  x = 7 y = 13 - (7)^2 + 2(7) y = 13 - 49 + 14 y = -22 x = -2 y = 13 - (-2)^2 + 2(-2) y = 13 - 4 - 4 y = 5 (7, -22) (-2, 5)"
     ],
     "responses": [
      "correct"
     ]
    },
    {
     "tag": "question_15_Solution",
     "patterns": [
      "9(2)^2+4y^2=36 36+4y^2=36 y=0",
      "9(x)^2 + 4(y)^2 = 36 x = 2 9(2)^2 + 4(y)^2 = 36 36 + 4(y)^2 = 36 4(y)^2 = 0 y^2 = 0 y=0"
     ],
     "responses": [
      "correct"
     ]
    }
   ]
  },
  {
   "item": [
    {
     "tag": "question_17_Answer",
     "patterns": [
      "(1,-2)",
      "1,-2"
     ],
     "responses": [
      "correct"
     ]
    },
    {
     "tag": "question_19_Answer",
     "patterns": [
      "(0,-4)(-2v3,2)(2v3,2)",
      "(0,-4)(-2v3,2)(2v3,2)"
     ],
     "responses": [
      "correct"
     ]
    },
    {
     "tag": "question_34_Answer",
     "patterns": [
      "(-2, -4) (-2,4) (2,-4) (2,4)",
      "(-2, -4),(-2,4),(2,-4),(2,4)"
     ],
     "responses": [
      "correct"
     ]
    },
    {
     "tag": "question_18_Answer",
     "patterns": [
      "x=1,y=-2",
      "x=1,y=-2"
     ],
     "responses": [
      "correct"
     ]
    },
    {
     "tag": "question_20_Answer",
     "patterns": [
      "(0,-3)(-v5,2)(v5,2)",
      "(0,-3)(-v5,2)(v5,2)"
     ],
     "responses": [
      "correct"
     ]
    },
    {
     "tag": "question_16_Answer",
     "patterns": [
      "(5,3),(5,-3),(-5,3),(-5,-3)",
      "5,3 5,-3 -5,3 -5,-3"
     ],
     "responses": [
      "correct"
     ]
    }
   ]
  },
  {
   "item": [
    {
     "tag": "question_17_Solution",
     "patterns": [
      "-8x-6y=4 8x-2y=12 -8y=16 y=-2 4x+3(-2)=-2 4x-6=-2 4x=4 x=1",
      "2(4x + 3y) = 2(-2) 8x + 6y = -4 3(8x - 2y) = 3(12) 24x - 6y = 36 8x + 6y = -4 24x - 6y = 36 (8x + 6y) + (24x - 6y) = -4 + 36 32x = 32 x = 1 4(1) + 3y = -2 4 + 3y = -2 3y = -6 y = -2 (1, -2)"
     ],
     "responses": [
      "correct"
     ]
    },
    {
     "tag": "question_19_Solution",
     "patterns": [
      "x^2+y^2=16 - x^2-2y=8 x^2+y^2-(x^2-2y)=16-8 y^2+2y=8 y=2 y=-4 x=2v3 x=-2v3 x=0",
      "x^2 + y^2 - (x^2 - 2y) = 16 - 8 y^2 + 2y = 8 y^2 + 2y = 8: y = 2, y = -4 y = 2, y = -4 x^2 + y^2 = 16 x^2 + y^2 = 16 2 x = 2V3, x = -2V3 x^2 + y^2 = 16 -4: x = 0 (0, -4) (-2V3, 2) (2V3, 2)"
     ],
     "responses": [
      "correct"
     ]
    },
    {
     "tag": "question_34_Solution",
     "patterns": [
      "x^2 + y^2 = 20 + x^2 - y^2 = -12 x^2 + y^2 + (x^2 - y^2) = 20 + (-12 ) 2x^2 = 8 x = 2, x = -2 y = 4, y = -4  y = 4, y = -4",
      "(x^2 + y^2) - (x^2 - y^2) = 20 - (-12) 2y^2 = 32 y^2 = 16 y = +/-4 x^2 + 16 = 20 x^2 = 4 x = +/- 2"
     ],
     "responses": [
      "correct"
     ]
    },
    {
     "tag": "question_18_Solution",
     "patterns": [
      "15x-10y=-5 8x-10y=28 (15x+10y)+(8x-10y)=-5+28 15x+10y+8x-107=23 23x=23 x=1 3x+2y=-1 3(1)+2y=-1 2y=-4 y=-2 x=1 y=-2",
      "4(3x + 2y) = 4(-1) 3(4x - 5y) = 3(14) 12x + 8y = -4 12x - 15y = 42 (12x + 8y) - (12x - 15y) = -4 - 42 23y = -46 y = -2 3x + 2(-2) = -1 3x - 4 = -1 3x = 3 x = 1 (1, -2)"
     ],
     "responses": [
      "correct"
     ]
    },
    {
     "tag": "question_20_Solution",
     "patterns": [
      "x^2+y^2=9 - x^2-y=3 x^2+y-(x^2-y)=9-3 y=2 y=3 x=v5 x=-v5 x=0",
      "(x^2 + y^2) - (x^2 - y) = 9 - 3 x^2 + y^2 - x^2 + y = 6 y^2 + y = 6 y^2 + y - 6 = 0 (y + 3)(y - 2) = 0 y = -3 y = 2 y = -3 x^2 + (-3)^2 = 9 x^2 + 9 = 9 x^2 = 0 x = 0  y = 2 x^2 + 2^2 = 9 x^2 + 4 = 9 x^2 = 5 x = +/- V5"
     ],
     "responses": [
      "correct"
     ]
    },
    {
     "tag": "question_16_Solution",
     "patterns": [
      "(x^2+y^2=34)2 2x^2+2y^2=68 2x^2+2y^2=68 + (x^2-2y=7) 3x^2=75 3x^2=75 x^2=25 x=+/-5 y^2=34-x^2 y^2=34-25 y^2=9 y=+/-3",
      "x^2 + y^2 - x^2 + 2y^2 = 27 3y^2 = 27 y^2 = 9 y = +/- 3 y = 3 x^2 + 3^2 = 34 x^2 + 9 = 34 x^2 = 25 x = +/-5 y = 3 x^2 + (-3)^2 = 34 x^2 + 9 = 34 x^2 = 25 x = +/-5 (5, 3) (-5, 3) (5, -3) (-5, -3)"
     ],
     "responses": [
      "correct"
     ]
    }
   ]
  }
 ]
}